CHANGES.txt
LICENCE.txt
MANIFEST.in
README.md
setup.py
pyschelling/GUI.py
pyschelling/__init__.py
pyschelling/model.py
pyschelling.egg-info/PKG-INFO
pyschelling.egg-info/SOURCES.txt
pyschelling.egg-info/dependency_links.txt
pyschelling.egg-info/entry_points.txt
pyschelling.egg-info/requires.txt
pyschelling.egg-info/top_level.txt